mkdocs_encrypt_source_plugin/__init__.py
mkdocs_encrypt_source_plugin/cli_tool.py
mkdocs_encrypt_source_plugin/mkdocs_plugin.py
mkdocs_encrypt_source_plugin-0.0.1.dist-info/LICENSE
mkdocs_encrypt_source_plugin-0.0.1.dist-info/METADATA
mkdocs_encrypt_source_plugin-0.0.1.dist-info/WHEEL
mkdocs_encrypt_source_plugin-0.0.1.dist-info/entry_points.txt
mkdocs_encrypt_source_plugin-0.0.1.dist-info/top_level.txt
mkdocs_encrypt_source_plugin-0.0.1.dist-info/RECORD
