Metadata-Version: 2.1
Name: mkdocs-encrypt-source-plugin
Version: 0.0.1
Summary: Store some information encrypted in the source code and decrypt when building the site
Home-page: https://github.com/six-two/mkdocs-encrypt-source-plugin
Author: six-two
Author-email: pip@six-two.dev
License: MIT License
Classifier: License :: OSI Approved :: MIT License
Classifier: Operating System :: POSIX :: Linux
Classifier: Programming Language :: Python :: 3
Classifier: Programming Language :: Python :: 3.9
Classifier: Programming Language :: Python :: 3.10
Classifier: Programming Language :: Python :: 3.11
Requires-Python: >=3.9
License-File: LICENSE
Requires-Dist: mkdocs >=1.4.0
Requires-Dist: cryptography
